sotam/__init__.py
sotam/sotam.py
sotam-0.2.2.dist-info/METADATA
sotam-0.2.2.dist-info/WHEEL
sotam-0.2.2.dist-info/top_level.txt
sotam-0.2.2.dist-info/RECORD
