Metadata-Version: 2.1
Name: sotam
Version: 0.2.2
Summary: SOTAM-VLSTM: A versatile LSTM framework for diverse tasks, cutting workload by ~40% with automation and multi-GPU support.
Home-page: https://github.com/anand-lab-172/SOTAM
Author: Anandaram Ganapathi
Author-email: anandaram.ganapathi@gmail.com
License: MIT
Classifier: Programming Language :: Python :: 3
Classifier: License :: OSI Approved :: MIT License
Classifier: Operating System :: OS Independent
Requires-Python: >=3.6
Requires-Dist: numpy (>=1.21.0)
Requires-Dist: pandas (>=1.3.0)
Requires-Dist: scikit-learn (>=1.0)
Requires-Dist: tensorflow (>=2.6.0)
Requires-Dist: keras (>=2.6.0)
Requires-Dist: plotly (>=5.0.0)
